[
  {
    "title": "100 Days of Code",
    "slug": "project-1",
    "description": "A selection of projects I worked on as part of my 100 days of code challenge.",
    "image": "/images/projects/project-1.png",
    "githubURL": "https://github.com/made-by-max/100daysofcode",
    "liveSiteURL": "https://radcode.netlify.app/"
  },
  {
    "title": "Twimba",
    "slug": "project-2",
    "description": "A Twitter clone I created for Scrimba's Frontend Developer Career Track",
    "image": "/images/projects/project-2.png",
    "githubURL": "https://github.com/made-by-max/twimba",
    "liveSiteURL": "https://joyful-meerkat-63cc2a.netlify.app/"
  }
  
]
